ice_ken/__init__.py
ice_ken/kennitala.py
ice_ken/loaders.py
ice_ken-1.1.0.dist-info/licenses/LICENSE
ice_ken-1.1.0.dist-info/METADATA
ice_ken-1.1.0.dist-info/WHEEL
ice_ken-1.1.0.dist-info/top_level.txt
ice_ken-1.1.0.dist-info/RECORD
