Metadata-Version: 2.4
Name: ice-ken
Version: 1.1.0
Summary: Utilities for managing Icelandic national IDs (kennitala) safely and efficiently
Author: Vignir Lydsson
License: GPL-3.0-or-later
Project-URL: Homepage, https://github.com/vignirvignir/ice-ken
Project-URL: Repository, https://github.com/vignirvignir/ice-ken
Keywords: kennitala,iceland,national-id,validation,utilities
Classifier: Programming Language :: Python :: 3
Classifier: Programming Language :: Python :: 3.9
Classifier: Programming Language :: Python :: 3.10
Classifier: Programming Language :: Python :: 3.11
Classifier: Programming Language :: Python :: 3.12
Classifier: Programming Language :: Python :: 3.13
Classifier: License :: OSI Approved :: GNU General Public License v3 or later (GPLv3+)
Classifier: Operating System :: OS Independent
Classifier: Intended Audience :: Developers
Classifier: Topic :: Software Development :: Libraries
Requires-Python: >=3.9
License-File: LICENSE
Dynamic: license-file
